pywrenfold.cpython-311-x86_64-linux-gnu.so
pywrenfold/__init__.pyi
pywrenfold/ast.pyi
pywrenfold/enumerations.pyi
pywrenfold/exceptions.pyi
pywrenfold/gen.pyi
pywrenfold/geometry.pyi
pywrenfold/sym.pyi
pywrenfold/sympy_conversion.pyi
pywrenfold/type_info.pyi
wrenfold/__init__.py
wrenfold/ast.py
wrenfold/code_generation.py
wrenfold/custom_types.py
wrenfold/enumerations.py
wrenfold/exceptions.py
wrenfold/external_functions.py
wrenfold/geometry.py
wrenfold/sym.py
wrenfold/sympy_conversion.py
wrenfold/type_annotations.py
wrenfold/type_info.py
wrenfold-0.5.1.data/headers/LICENSE
wrenfold-0.5.1.data/headers/span.h
wrenfold-0.5.1.data/headers/span_detail.h
wrenfold-0.5.1.dist-info/METADATA
wrenfold-0.5.1.dist-info/WHEEL
wrenfold-0.5.1.dist-info/RECORD
wrenfold-0.5.1.dist-info/licenses/LICENSE
wrenfold-0.5.1.dist-info/licenses/dependencies/abseil-cpp/LICENSE
wrenfold-0.5.1.dist-info/licenses/dependencies/eigen/LICENSE
wrenfold-0.5.1.dist-info/licenses/dependencies/fmt/LICENSE
wrenfold-0.5.1.dist-info/licenses/dependencies/nanobind/LICENSE
