Metadata-Version: 2.2
Name: wrenfold
Version: 0.5.1
Summary: Tools for code-generating mathematical functions.
Keywords: symbolic,math,code-generation,robotics,vision
Author-Email: Gareth Cross <gcross.code@icloud.com>
License: MIT
Classifier: Development Status :: 3 - Alpha
Classifier: Intended Audience :: Developers
Classifier: Intended Audience :: Science/Research
Classifier: Topic :: Scientific/Engineering :: Mathematics
Classifier: Topic :: Software Development :: Code Generators
Classifier: Programming Language :: Python :: 3.10
Classifier: Programming Language :: Python :: 3.11
Classifier: Programming Language :: Python :: 3.12
Classifier: Programming Language :: Python :: 3.13
Classifier: Programming Language :: Python :: 3.14
Project-URL: Homepage, https://wrenfold.org
Project-URL: Repository, https://github.com/wrenfold/wrenfold/
Project-URL: Issues, https://github.com/wrenfold/wrenfold/issues
Requires-Python: >=3.10
